ibm_quantum_widgets/__init__.py
ibm_quantum_widgets/_frontend.py
ibm_quantum_widgets/_version.py
ibm_quantum_widgets/circuit_composer.py
ibm_quantum_widgets/draw_circuit.py
ibm_quantum_widgets/edit_circuit.py
ibm_quantum_widgets/serializers.py
ibm_quantum_widgets/utils.py
ibm_quantum_widgets/nbextension/__init__.py
ibm_quantum_widgets/tests/__init__.py
ibm_quantum_widgets/tests/conftest.py
ibm_quantum_widgets/tests/test_example.py
ibm_quantum_widgets/tests/test_nbextension_path.py
ibm_quantum_widgets-1.0.3.data/data/etc/jupyter/nbconfig/notebook.d/ibm_quantum_widgets.json
ibm_quantum_widgets-1.0.3.data/data/share/jupyter/lab/extensions/quantum-ibm-q-lab-widgets-1.0.3.tgz
ibm_quantum_widgets-1.0.3.data/data/share/jupyter/nbextensions/ibm_quantum_widgets/0.index.js
ibm_quantum_widgets-1.0.3.data/data/share/jupyter/nbextensions/ibm_quantum_widgets/2.index.js
ibm_quantum_widgets-1.0.3.data/data/share/jupyter/nbextensions/ibm_quantum_widgets/3.index.js
ibm_quantum_widgets-1.0.3.data/data/share/jupyter/nbextensions/ibm_quantum_widgets/4.index.js
ibm_quantum_widgets-1.0.3.data/data/share/jupyter/nbextensions/ibm_quantum_widgets/extension.js
ibm_quantum_widgets-1.0.3.data/data/share/jupyter/nbextensions/ibm_quantum_widgets/index.js
ibm_quantum_widgets-1.0.3.dist-info/LICENSE.txt
ibm_quantum_widgets-1.0.3.dist-info/METADATA
ibm_quantum_widgets-1.0.3.dist-info/WHEEL
ibm_quantum_widgets-1.0.3.dist-info/top_level.txt
ibm_quantum_widgets-1.0.3.dist-info/RECORD
